mp_boilerplate/EPTS.py
mp_boilerplate/__init__.py
mp_boilerplate/core/MultiWorker.py
mp_boilerplate/core/__init__.py
mp_boilerplate-0.3.4.dist-info/LICENSE
mp_boilerplate-0.3.4.dist-info/METADATA
mp_boilerplate-0.3.4.dist-info/WHEEL
mp_boilerplate-0.3.4.dist-info/top_level.txt
mp_boilerplate-0.3.4.dist-info/RECORD
