Metadata-Version: 2.1
Name: mp-boilerplate
Version: 0.3.4
Summary: A collection of patterns to use over top of the built in multiprocessing package
Home-page: https://github.com/markanewman/mp_boilerplate
Author: @markanewman
Author-email: mp_boilerplate@trinetteandmark.com
License: UNKNOWN
Project-URL: Bug Reports, https://github.com/markanewman/mp_boilerplate/issues
Project-URL: Source, https://github.com/markanewman/mp_boilerplate
Platform: UNKNOWN
Classifier: Development Status :: 4 - Beta
Classifier: Intended Audience :: Developers
Classifier: License :: OSI Approved :: MIT License
Classifier: Natural Language :: English
Classifier: Operating System :: OS Independent
Classifier: Programming Language :: Python :: 3
Classifier: Topic :: Software Development :: Libraries :: Python Modules
Classifier: Topic :: Utilities
Requires-Python: >=3.6, <4
Requires-Dist: progressbar2 (<4.0.0,>=3.51.4)
Requires-Dist: typeguard (<3.0.0,>=2.7.1)
